{
    "arrow-down": "arrow-down.svg",
    "artwork": "artwork.svg",
    "auction": "auction.svg",
    "check": "check.svg",
    "chevron-down": "chevron-down.svg",
    "chevron-left": "chevron-left.svg",
    "chevron-right": "chevron-right.svg",
    "chevron-small-down": "chevron-small-down.svg",
    "chevron-small-left": "chevron-small-left.svg",
    "chevron-small-right": "chevron-small-right.svg",
    "chevron-small-up": "chevron-small-up.svg",
    "chevron-up": "chevron-up.svg",
    "circle-check": "circle-check.svg",
    "circle-chevron": "circle-chevron.svg",
    "circle-plus": "circle-plus.svg",
    "close": "close.svg",
    "download": "download.svg",
    "edit": "edit.svg",
    "ellipsis": "ellipsis.svg",
    "facebook": "facebook.svg",
    "frame": "frame.svg",
    "grid": "grid.svg",
    "heart": "heart.svg",
    "info-filled": "info-filled.svg",
    "info": "info.svg",
    "instagram": "instagram.svg",
    "link": "link.svg",
    "list": "list.svg",
    "logo-unscaled": "logo-unscaled.svg",
    "logo": "logo.svg",
    "logotype-unscaled": "logotype-unscaled.svg",
    "logotype": "logotype.svg",
    "mail": "mail.svg",
    "minus-small": "minus-small.svg",
    "person": "person.svg",
    "pinterest": "pinterest.svg",
    "plus-small": "plus-small.svg",
    "remove-small": "remove-small.svg",
    "search": "search.svg",
    "share": "share.svg",
    "tumblr": "tumblr.svg",
    "twitter": "twitter.svg",
    "view-in-room": "view-in-room.svg",
    "website": "website.svg",
    "write": "write.svg"
}